clinisift/__init__.py
clinisift/cliniparse.py
clinisift/doc.py
clinisift/utils.py
clinisift/visualize.py
clinisift-0.0.3.dist-info/LICENSE
clinisift-0.0.3.dist-info/METADATA
clinisift-0.0.3.dist-info/WHEEL
clinisift-0.0.3.dist-info/top_level.txt
clinisift-0.0.3.dist-info/RECORD
