Metadata-Version: 2.1
Name: clinisift
Version: 0.0.3
Summary: An NLP tool for parsing, analyzing, and visualizing medical records
Home-page: https://github.com/clinisift/clinisift
Author: Sam Rawal
Author-email: scrawal2@illinois.edu
Project-URL: Bug Tracker, https://github.com/clinisift/clinisift/issues
Classifier: Programming Language :: Python :: 3
Classifier: License :: OSI Approved :: MIT License
Classifier: Operating System :: OS Independent
Requires-Python: >=3.6
License-File: LICENSE
Requires-Dist: torch (>=1.8.0)
Requires-Dist: transformers (>=4.4.1)
Requires-Dist: nltk (>=3.5)
Requires-Dist: spacy (>=3.0)
Requires-Dist: Flask (==1.1.2)
